common/AnsibleHelper.py
common/InventoryHelper.py
common/Utils.py
common/__init__.py
tools_automator-0.0.5.dist-info/METADATA
tools_automator-0.0.5.dist-info/WHEEL
tools_automator-0.0.5.dist-info/entry_points.txt
tools_automator-0.0.5.dist-info/top_level.txt
tools_automator-0.0.5.dist-info/RECORD
