Metadata-Version: 2.1
Name: tools-automator
Version: 0.0.5
Summary: UNKNOWN
Home-page: UNKNOWN
Author: João André Simões
Author-email: jarpsimoes@gmail.com
License: MIT
Platform: UNKNOWN
Classifier: License :: OSI Approved :: MIT License
Classifier: Programming Language :: Python :: 3
Classifier: Programming Language :: Python :: 3.7
Requires-Dist: Click
Requires-Dist: pexpect
Requires-Dist: ansible
